asis.py
setup.py
asis.egg-info/PKG-INFO
asis.egg-info/SOURCES.txt
asis.egg-info/dependency_links.txt
asis.egg-info/requires.txt
asis.egg-info/top_level.txt
bin/asis-server