Metadata-Version: 1.0
Name: asis
Version: 0.2
Summary: Lightweight As-Is Server
Home-page: http://github.com/seomoz/asis-server
Author: Dan Lecocq
Author-email: dan@seomoz.org
License: UNKNOWN
Platform: Posix; MacOS X
Classifier: Development Status :: 3 - Alpha
Classifier: Environment :: Console
Classifier: Intended Audience :: Developers
Classifier: Topic :: System :: Shells
